wtdojo/__init__.py
wtdojo/__init__.py.bak
wtdojo/__init__.pyc
wtdojo/validators.py
wtdojo/validators.py.bak
wtdojo/validators.pyc
wtdojo/__pycache__/__init__.cpython-34.pyc
wtdojo/__pycache__/__init__.cpython-35.pyc
wtdojo/__pycache__/__init__.cpython-38.pyc
wtdojo/__pycache__/validators.cpython-34.pyc
wtdojo/__pycache__/validators.cpython-35.pyc
wtdojo/__pycache__/validators.cpython-38.pyc
wtdojo/fields/__init__.py
wtdojo/fields/__init__.py.bak
wtdojo/fields/__init__.pyc
wtdojo/fields/core.py
wtdojo/fields/core.pyc
wtdojo/fields/__pycache__/__init__.cpython-34.pyc
wtdojo/fields/__pycache__/__init__.cpython-35.pyc
wtdojo/fields/__pycache__/__init__.cpython-38.pyc
wtdojo/fields/__pycache__/core.cpython-34.pyc
wtdojo/fields/__pycache__/core.cpython-35.pyc
wtdojo/fields/__pycache__/core.cpython-38.pyc
wtdojo/widgets/__init__.py
wtdojo/widgets/__init__.py.bak
wtdojo/widgets/__init__.pyc
wtdojo/widgets/core.py
wtdojo/widgets/core.py.bak
wtdojo/widgets/core.pyc
wtdojo/widgets/__pycache__/__init__.cpython-34.pyc
wtdojo/widgets/__pycache__/__init__.cpython-35.pyc
wtdojo/widgets/__pycache__/__init__.cpython-38.pyc
wtdojo/widgets/__pycache__/core.cpython-34.pyc
wtdojo/widgets/__pycache__/core.cpython-35.pyc
wtdojo/widgets/__pycache__/core.cpython-38.pyc
wtdojo-0.3.dist-info/METADATA
wtdojo-0.3.dist-info/WHEEL
wtdojo-0.3.dist-info/top_level.txt
wtdojo-0.3.dist-info/RECORD
