Metadata-Version: 2.1
Name: wtdojo
Version: 0.3
Summary: Dojo javascript toolkit support for WTForms
Home-page: http://pypi.python.org/pypi/wtdojo
Author: Kashif Iftikhar
Author-email: kashif@compulife.com.pk
License: UNKNOWN
Keywords: wtforms dojo
Platform: UNKNOWN
Classifier: Programming Language :: Python
Classifier: Topic :: Internet :: WWW/HTTP
Requires-Dist: wtforms
